{
  "appPageId" : "c836e865-a6a0-4a8d-9ed8-54b0752d465f",
  "componentName" : "community_layout:sldsFlexibleLayout",
  "id" : "4fe26827-2d4e-496b-a591-6edd73aafd1d",
  "label" : "Home",
  "regions" : [ {
    "components" : [ {
      "componentAttributes" : {
        "sectionConfig" : "{\"UUID\":\"3ba83866-9da1-4d48-aa6d-cd07d9b7de14\",\"columns\":[{\"UUID\":\"f6239b4b-cad2-4a75-a312-d572e40f3aff\",\"columnName\":\"Column 1\",\"columnKey\":\"col1\",\"columnWidth\":\"12\",\"seedComponents\":null}]}"
      },
      "componentName" : "community_layout:section",
      "id" : "3ba83866-9da1-4d48-aa6d-cd07d9b7de14",
      "regions" : [ {
        "components" : [ {
          "componentAttributes" : {
            "richTextValue" : "<div style=\"display: flex; justify-content: center; align-items: center; margin: 50px 0; flex-direction: column; text-align: center;\"><div style=\"background-image: var(--lwc-header-image); background-size: cover; background-position: center; height: 300px; width: 100%; max-width: 600px; min-width: 300px;\"></div><h1 class=\"slds-text-heading_medium slds-p-bottom_x-small\">Start Building Your Page</h1> <div>Drag and drop a component into the content slots.</div></div>"
          },
          "componentName" : "community_builder:htmlEditor",
          "id" : "fad6cafa-dd8c-453a-8103-1f4ed35d24d2",
          "renderPriority" : "NEUTRAL",
          "renditionMap" : { },
          "type" : "component"
        } ],
        "id" : "f6239b4b-cad2-4a75-a312-d572e40f3aff",
        "regionLabel" : "Column 1",
        "regionName" : "col1",
        "renditionMap" : { },
        "type" : "region"
      } ],
      "renderPriority" : "NEUTRAL",
      "renditionMap" : { },
      "type" : "component"
    } ],
    "id" : "45be997a-51b8-467a-b66f-91e83f6ac64c",
    "regionName" : "content",
    "type" : "region"
  }, {
    "components" : [ {
      "componentAttributes" : {
        "description" : "",
        "metaTags" : "",
        "pageTitle" : "Home",
        "recordId" : "{!recordId}"
      },
      "componentName" : "community_builder:seoAssistant",
      "id" : "3dab7443-0f7e-4b68-9387-51ec335d273b",
      "renderPriority" : "NEUTRAL",
      "renditionMap" : { },
      "type" : "component"
    } ],
    "id" : "4f05bd61-987a-4c8d-9b17-92213a277c4c",
    "regionName" : "sfdcHiddenRegion",
    "type" : "region"
  } ],
  "themeLayoutType" : "Inner",
  "type" : "view",
  "viewType" : "home"
}